authorization/__init__.py
authorization/authorization.py
authorization/credentials.py
python_authorization/__init__.py
python_authorization/authorization.py
python_authorization/credentials.py
python_authorization-1.0.3.dist-info/METADATA
python_authorization-1.0.3.dist-info/WHEEL
python_authorization-1.0.3.dist-info/top_level.txt
python_authorization-1.0.3.dist-info/RECORD
